Workbook

Sheet CABEÇALHO
A5: FUNCIONÁRIO:
A6: SAFRA: | H6: ANO DO EXERCÍCIO:
A7: RELATÓRIO DE CUSTOS VARIÁVEIS (C.V.).

Sheet NORMAS

Sheet BANCO DE DADOS
B5: =CABEÇALHO!B5 -> 0
B6: CUSTOS TOTAIS DE C.V. RECEBIDO | F6: AJUDA DE CUSTOS RECEBIDA
B7: =C95 -> 0 | F7: =G27 -> 0
B8: TOTAL DE GASTO ACUMULADO DE C.V. | F8: TOTAL DE GASTO ACUMULADO DE AJUDA DE CUSTOS
B9: =RDM_RDA!F2 -> 0 | F9: ='AJUDA DE CUSTOS'!E2 -> 0
B10: SALDO DE C.V. RECEBIDO | F10: SALDO DE AJUDA DE CUSTOS RECEBIDO
B11: =B7-B9 -> 0 | F11: =F7-F9 -> 0
B12: Inserir COM ATENÇÃO abaixo, todo o valor repassado para as despesas mensais!
B13: EXTRATO DE VALOR RECEBIDO | F13: AJUDA DE CUSTO RECEBIDO | I13: REEMBOLSO DE: | J13: =SUM('CV REEMBOLSO'!E59:H59,'CV REEMBOLSO'!E118:H118,'CV REEMBOLSO'!E177:H177,'CV REEMBOLSO'!E236:H236,'CV REEMBOLSO'!E295:H295,'CV REEMBOLSO'!E354:H354,'CV REEMBOLSO'!E413:H413,'CV REEMBOLSO'!E472:H472,'CV REEMBOLSO'!E531:H531,'CV REEMBOLSO'!E591:H591,'CV REEMBOLSO'!E651:H651,'CV REEMBOLSO'!E711:H711)-J95 -> 0
B14: DATA | C14: R$ | F14: DATA | G14: R$ | I14: DATA | J14: R$
F27: TOTAL | G27: =SUM(G15:G26) -> 0
B95: TOTAL | C95: =SUBTOTAL(9,C15:C94) -> 0 | I95: TOTAL PAGO | J95: =SUM(J15:J94) -> 0

Sheet RDM_RDA
A1: CUSTOS VARIÁVEIS (C.V.)
A2: TOTAL DE GASTO ACUMULADO | F2: =SUM(E59,E118,E177,E236,E295,E354,E413,E472,E531,E591,E651,E711) -> 0 | G2: TOTAL RECEBIDO | K2: ='BANCO DE DADOS'!C95 -> 0 | L2: SALDO | P2: =D2-H2 -> 0
A3: ABASTECIMENTO | E3: HOSPEDAGENS | I3: ALIMENTAÇÃO | M3: OUTROS (BORRACHARIA/OFICINA/EPI'S)
A4: DATA | B4: CNPJ DA NOTA | C4: Nº DA NOTA: | D4: R$ | E4: DATA | F4: CNPJ DA NOTA | G4: Nº DA NOTA: | H4: R$ | I4: DATA | J4: CNPJ DA NOTA | K4: Nº DA NOTA: | L4: R$ | M4: DATA | N4: CNPJ DA NOTA | O4: Nº DA NOTA: | P4: R$
A5: JANEIRO
A58: TOTAL DE GASTOS | D58: =SUM(D6:D57) -> 0 | E58: TOTAL DE GASTOS | H58: =SUM(H6:H57) -> 0 | I58: TOTAL DE GASTOS | L58: =SUM(L6:L57) -> 0 | M58: TOTAL DE GASTOS | P58: =SUM(P6:P57) -> 0
E59: =SUM(D58,H58,L58,P58) -> 0
A61: FEVEREIRO
A117: TOTAL DE GASTOS | D117: =SUM(D62:D116) -> 0 | E117: TOTAL DE GASTOS | H117: =SUM(H62:H116) -> 0 | I117: TOTAL DE GASTOS | L117: =SUM(L62:L116) -> 0 | M117: TOTAL DE GASTOS | P117: =SUM(P62:P116) -> 0
E118: =SUM(D117,H117,L117,P117) -> 0
A120: MARÇO
A176: TOTAL DE GASTOS | D176: =SUM(D121:D175) -> 0 | E176: TOTAL DE GASTOS | H176: =SUM(H121:H175) -> 0 | I176: TOTAL DE GASTOS | L176: =SUM(L121:L175) -> 0 | M176: TOTAL DE GASTOS | P176: =SUM(P121:P175) -> 0
E177: =SUM(D176,H176,L176,P176) -> 0
A179: ABRIL
A235: TOTAL DE GASTOS | D235: =SUM(D180:D234) -> 0 | E235: TOTAL DE GASTOS | H235: =SUM(H180:H234) -> 0 | I235: TOTAL DE GASTOS | L235: =SUM(L180:L234) -> 0 | M235: TOTAL DE GASTOS | P235: =SUM(P180:P234) -> 0
E236: =SUM(D235,H235,L235,P235) -> 0
A238: MAIO
A294: TOTAL DE GASTOS | D294: =SUM(D239:D293) -> 0 | E294: TOTAL DE GASTOS | H294: =SUM(H239:H293) -> 0 | I294: TOTAL DE GASTOS | L294: =SUM(L239:L293) -> 0 | M294: TOTAL DE GASTOS | P294: =SUM(P239:P293) -> 0
E295: =SUM(D294,H294,L294,P294) -> 0
A297: JUNHO
A353: TOTAL DE GASTOS | D353: =SUM(D298:D352) -> 0 | E353: TOTAL DE GASTOS | H353: =SUM(H298:H352) -> 0 | I353: TOTAL DE GASTOS | L353: =SUM(L298:L352) -> 0 | M353: TOTAL DE GASTOS | P353: =SUM(P298:P352) -> 0
E354: =SUM(D353,H353,L353,P353) -> 0
A356: JULHO
A412: TOTAL DE GASTOS | D412: =SUM(D357:D411) -> 0 | E412: TOTAL DE GASTOS | H412: =SUM(H357:H411) -> 0 | I412: TOTAL DE GASTOS | L412: =SUM(L357:L411) -> 0 | M412: TOTAL DE GASTOS | P412: =SUM(P357:P411) -> 0
E413: =SUM(D412,H412,L412,P412) -> 0
A415: AGOSTO
A471: TOTAL DE GASTOS | D471: =SUM(D416:D470) -> 0 | E471: TOTAL DE GASTOS | H471: =SUM(H416:H470) -> 0 | I471: TOTAL DE GASTOS | L471: =SUM(L416:L470) -> 0 | M471: TOTAL DE GASTOS | P471: =SUM(P416:P470) -> 0
E472: =SUM(D471,H471,L471,P471) -> 0
A474: SETEMBRO
A530: TOTAL DE GASTOS | D530: =SUM(D475:D529) -> 0 | E530: TOTAL DE GASTOS | H530: =SUM(H475:H529) -> 0 | I530: TOTAL DE GASTOS | L530: =SUM(L475:L529) -> 0 | M530: TOTAL DE GASTOS | P530: =SUM(P475:P529) -> 0
E531: =SUM(D530,H530,L530,P530) -> 0
A533: OUTUBRO
A590: TOTAL DE GASTOS | D590: =SUM(D534:D589) -> 0 | E590: TOTAL DE GASTOS | H590: =SUM(H534:H589) -> 0 | I590: TOTAL DE GASTOS | L590: =SUM(L534:L589) -> 0 | M590: TOTAL DE GASTOS | P590: =SUM(P534:P589) -> 0
E591: =SUM(D590,H590,L590,P590) -> 0
A593: NOVEMBRO
A650: TOTAL DE GASTOS | D650: =SUM(D594:D649) -> 0 | E650: TOTAL DE GASTOS | H650: =SUM(H594:H649) -> 0 | I650: TOTAL DE GASTOS | L650: =SUM(L594:L649) -> 0 | M650: TOTAL DE GASTOS | P650: =SUM(P594:P649) -> 0
E651: =SUM(D650,H650,L650,P650) -> 0
A653: DEZEMBRO
A710: TOTAL DE GASTOS | D710: =SUM(D654:D709) -> 0 | E710: TOTAL DE GASTOS | H710: =SUM(H654:H709) -> 0 | I710: TOTAL DE GASTOS | L710: =SUM(L654:L709) -> 0 | M710: TOTAL DE GASTOS | P710: =SUM(P654:P709) -> 0
E711: =SUM(D710,H710,L710,P710) -> 0

Sheet CV REEMBOLSO
A1: CUSTOS VARIÁVEIS (C.V.)
A2: TOTAL DE GASTO ACUMULADO | F2: =SUM(E59,E118,E177,E236,E295,E354,E413,E472,E531,E591,E651,E711) -> 0 | G2: TOTAL RECEBIDO | K2: ='BANCO DE DADOS'!C95 -> 0 | L2: SALDO | P2: =D2-H2 -> 0
A3: ABASTECIMENTO | E3: HOSPEDAGENS | I3: ALIMENTAÇÃO | M3: OUTROS (BORRACHARIA/OFICINA/EPI'S)
A4: DATA | B4: CNPJ DA NOTA | C4: Nº DA NOTA: | D4: R$ | E4: DATA | F4: CNPJ DA NOTA | G4: Nº DA NOTA: | H4: R$ | I4: DATA | J4: CNPJ DA NOTA | K4: Nº DA NOTA: | L4: R$ | M4: DATA | N4: CNPJ DA NOTA | O4: Nº DA NOTA: | P4: R$
A5: JANEIRO
A58: TOTAL DE GASTOS | D58: =SUM(D6:D57) -> 0 | E58: TOTAL DE GASTOS | H58: =SUM(H6:H57) -> 0 | I58: TOTAL DE GASTOS | L58: =SUM(L6:L57) -> 0 | M58: TOTAL DE GASTOS | P58: =SUM(P6:P57) -> 0
E59: =SUM(D58,H58,L58,P58) -> 0
A61: FEVEREIRO
A117: TOTAL DE GASTOS | D117: =SUM(D62:D116) -> 0 | E117: TOTAL DE GASTOS | H117: =SUM(H62:H116) -> 0 | I117: TOTAL DE GASTOS | L117: =SUM(L62:L116) -> 0 | M117: TOTAL DE GASTOS | P117: =SUM(P62:P116) -> 0
E118: =SUM(D117,H117,L117,P117) -> 0
A120: MARÇO
A176: TOTAL DE GASTOS | D176: =SUM(D121:D175) -> 0 | E176: TOTAL DE GASTOS | H176: =SUM(H121:H175) -> 0 | I176: TOTAL DE GASTOS | L176: =SUM(L121:L175) -> 0 | M176: TOTAL DE GASTOS | P176: =SUM(P121:P175) -> 0
E177: =SUM(D176,H176,L176,P176) -> 0
A179: ABRIL
A235: TOTAL DE GASTOS | D235: =SUM(D180:D234) -> 0 | E235: TOTAL DE GASTOS | H235: =SUM(H180:H234) -> 0 | I235: TOTAL DE GASTOS | L235: =SUM(L180:L234) -> 0 | M235: TOTAL DE GASTOS | P235: =SUM(P180:P234) -> 0
E236: =SUM(D235,H235,L235,P235) -> 0
A238: MAIO
A294: TOTAL DE GASTOS | D294: =SUM(D239:D293) -> 0 | E294: TOTAL DE GASTOS | H294: =SUM(H239:H293) -> 0 | I294: TOTAL DE GASTOS | L294: =SUM(L239:L293) -> 0 | M294: TOTAL DE GASTOS | P294: =SUM(P239:P293) -> 0
E295: =SUM(D294,H294,L294,P294) -> 0
A297: JUNHO
A353: TOTAL DE GASTOS | D353: =SUM(D298:D352) -> 0 | E353: TOTAL DE GASTOS | H353: =SUM(H298:H352) -> 0 | I353: TOTAL DE GASTOS | L353: =SUM(L298:L352) -> 0 | M353: TOTAL DE GASTOS | P353: =SUM(P298:P352) -> 0
E354: =SUM(D353,H353,L353,P353) -> 0
A356: JULHO
A412: TOTAL DE GASTOS | D412: =SUM(D357:D411) -> 0 | E412: TOTAL DE GASTOS | H412: =SUM(H357:H411) -> 0 | I412: TOTAL DE GASTOS | L412: =SUM(L357:L411) -> 0 | M412: TOTAL DE GASTOS | P412: =SUM(P357:P411) -> 0
E413: =SUM(D412,H412,L412,P412) -> 0
A415: AGOSTO
A471: TOTAL DE GASTOS | D471: =SUM(D416:D470) -> 0 | E471: TOTAL DE GASTOS | H471: =SUM(H416:H470) -> 0 | I471: TOTAL DE GASTOS | L471: =SUM(L416:L470) -> 0 | M471: TOTAL DE GASTOS | P471: =SUM(P416:P470) -> 0
E472: =SUM(D471,H471,L471,P471) -> 0
A474: SETEMBRO
A530: TOTAL DE GASTOS | D530: =SUM(D475:D529) -> 0 | E530: TOTAL DE GASTOS | H530: =SUM(H475:H529) -> 0 | I530: TOTAL DE GASTOS | L530: =SUM(L475:L529) -> 0 | M530: TOTAL DE GASTOS | P530: =SUM(P475:P529) -> 0
E531: =SUM(D530,H530,L530,P530) -> 0
A533: OUTUBRO
A590: TOTAL DE GASTOS | D590: =SUM(D534:D589) -> 0 | E590: TOTAL DE GASTOS | H590: =SUM(H534:H589) -> 0 | I590: TOTAL DE GASTOS | L590: =SUM(L534:L589) -> 0 | M590: TOTAL DE GASTOS | P590: =SUM(P534:P589) -> 0
E591: =SUM(D590,H590,L590,P590) -> 0
A593: NOVEMBRO
A650: TOTAL DE GASTOS | D650: =SUM(D594:D649) -> 0 | E650: TOTAL DE GASTOS | H650: =SUM(H594:H649) -> 0 | I650: TOTAL DE GASTOS | L650: =SUM(L594:L649) -> 0 | M650: TOTAL DE GASTOS | P650: =SUM(P594:P649) -> 0
E651: =SUM(D650,H650,L650,P650) -> 0
A653: DEZEMBRO
A710: TOTAL DE GASTOS | D710: =SUM(D654:D709) -> 0 | E710: TOTAL DE GASTOS | H710: =SUM(H654:H709) -> 0 | I710: TOTAL DE GASTOS | L710: =SUM(L654:L709) -> 0 | M710: TOTAL DE GASTOS | P710: =SUM(P654:P709) -> 0
E711: =SUM(D710,H710,L710,P710) -> 0

Sheet AJUDA DE CUSTOS
B1: AJUDA DE CUSTOS
B2: TOTAL DE GASTO ACUMULADO | E2: =SUM(E36,E70,E104,E138,E172,E206,E240,E274,E308,E342,E376,E410) -> 0
B3: ABASTECIMENTO
B4: DATA | C4: CNPJ DA NOTA | D4: Nº DA NOTA: | E4: R$
A5: JANEIRO
B36: TOTAL DE GASTOS | E36: =SUM(E5:E35) -> 0
A39: FEVEREIRO
B70: TOTAL DE GASTOS | E70: =SUM(E39:E69) -> 0
A73: MARÇO
B104: TOTAL DE GASTOS | E104: =SUM(E73:E103) -> 0
A107: ABRIL
B138: TOTAL DE GASTOS | E138: =SUM(E107:E137) -> 0
A141: MAIO
B172: TOTAL DE GASTOS | E172: =SUM(E141:E171) -> 0
A175: JUNHO
B206: TOTAL DE GASTOS | E206: =SUM(E175:E205) -> 0
A209: JULHO
B240: TOTAL DE GASTOS | E240: =SUM(E209:E239) -> 0
A243: AGOSTO
B274: TOTAL DE GASTOS | E274: =SUM(E243:E273) -> 0
A277: SETEMBRO
B308: TOTAL DE GASTOS | E308: =SUM(E277:E307) -> 0
A311: OUTUBRO
B342: TOTAL DE GASTOS | E342: =SUM(E311:E341) -> 0
A345: NOVEMBRO
B376: TOTAL DE GASTOS | E376: =SUM(E345:E375) -> 0
A379: DEZEMBRO
B410: TOTAL DE GASTOS | E410: =SUM(E379:E409) -> 0
